yukkurimandarin/__init__.py
yukkurimandarin/core.py
yukkurimandarin/data/yinjie_database.db
yukkurimandarin/database.py
yukkurimandarin/database_mngr.py
yukkurimandarin/digit_to_chinese.py
yukkurimandarin/generate_gana.py
yukkurimandarin/generate_table.py
yukkurimandarin/hanzi_process.py
yukkurimandarin/non_hanzi_process.py
yukkurimandarin/post_process.py
yukkurimandarin/pre_process.py
yukkurimandarin/settings.py
yukkuri_mandarin-1.0.1.dist-info/METADATA
yukkuri_mandarin-1.0.1.dist-info/WHEEL
yukkuri_mandarin-1.0.1.dist-info/licenses/LICENSE
yukkuri_mandarin-1.0.1.dist-info/RECORD
