Metadata-Version: 2.4
Name: yukkuri-mandarin
Version: 1.0.1
Summary: 将汉语转换为“伪日本语”.
License: MIT
License-File: LICENSE
Keywords: mandarin,普通话,hiragana,平仮名
Author: wubzbz
Author-email: wubzbz@126.com
Requires-Python: >=3.9,<4
Classifier: Development Status :: 4 - Beta
Classifier: Intended Audience :: Developers
Classifier: License :: OSI Approved :: MIT License
Classifier: Natural Language :: Chinese (Simplified)
Classifier: Natural Language :: Chinese (Traditional)
Classifier: Natural Language :: Japanese
Classifier: Operating System :: OS Independent
Classifier: Programming Language :: Python :: 3
Classifier: Programming Language :: Python :: 3.9
Classifier: Programming Language :: Python :: 3.10
Classifier: Programming Language :: Python :: 3.11
Classifier: Programming Language :: Python :: 3.12
Classifier: Programming Language :: Python :: 3.13
Classifier: Programming Language :: Python :: 3.14
Classifier: Topic :: Text Processing
Classifier: Topic :: Utilities
Provides-Extra: all
Provides-Extra: jieba
Provides-Extra: openpyxl
Requires-Dist: jieba (>=0.42.1) ; extra == "all"
Requires-Dist: jieba (>=0.42.1) ; extra == "jieba"
Requires-Dist: openpyxl (>=3.1.5) ; extra == "all"
Requires-Dist: openpyxl (>=3.1.5) ; extra == "openpyxl"
Requires-Dist: pypinyin (>=0.54.0)
Project-URL: Documentation, https://github.com/wubzbz/Yukkuri-Mandarin#readme
Project-URL: Homepage, https://github.com/wubzbz/Yukkuri-Mandarin
Project-URL: Issues, https://github.com/wubzbz/Yukkuri-Mandarin/issues
Project-URL: Source, https://github.com/wubzbz/Yukkuri-Mandarin
